MCPTest/MCPServer.py
MCPTest/__init__.py
MCPTest/ragHandler.py
MCPTest/ragservertest.py
MCPTest/streamable_mcp_client.py
MCPTest/streamable_mcp_server.py
shizheng_mcpdemo_server-0.3.0.dist-info/METADATA
shizheng_mcpdemo_server-0.3.0.dist-info/WHEEL
shizheng_mcpdemo_server-0.3.0.dist-info/entry_points.txt
shizheng_mcpdemo_server-0.3.0.dist-info/top_level.txt
shizheng_mcpdemo_server-0.3.0.dist-info/RECORD
