Metadata-Version: 2.4
Name: shizheng-mcpdemo-server
Version: 0.3.0
Summary: Sample program used for testing the MCP service
Requires-Python: >=3.12
Requires-Dist: fastapi>=0.115.14
Requires-Dist: fastapi-mcp>=0.3.4
Requires-Dist: langchain>=0.3.26
Requires-Dist: langgraph==0.4.5
Requires-Dist: langgraph-sdk>=0.1.72
Requires-Dist: uvicorn==0.34.2
